{
  "coverage": "0%",
  "expectCount": 5,
  "actualCount": 0,
  "files": {
    "src/component/Create-Goal/styles.js": {
      "expectCount": 1,
      "actualCount": 0,
      "undocumentLines": [
        3
      ]
    },
    "src/component/Home-Page/styles.js": {
      "expectCount": 1,
      "actualCount": 0,
      "undocumentLines": [
        3
      ]
    },
    "src/component/If/If.js": {
      "expectCount": 1,
      "actualCount": 0,
      "undocumentLines": [
        1
      ]
    },
    "src/context/app-state-context.js": {
      "expectCount": 1,
      "actualCount": 0,
      "undocumentLines": [
        3
      ]
    },
    "src/context/navigation-context.js": {
      "expectCount": 1,
      "actualCount": 0,
      "undocumentLines": [
        3
      ]
    }
  }
}